quart_imp/__init__.py
quart_imp/exceptions.py
quart_imp/imp.py
quart_imp/imp_blueprint.py
quart_imp/protocols.py
quart_imp/utilities.py
quart_imp/_cli/__init__.py
quart_imp/_cli/blueprint.py
quart_imp/_cli/helpers.py
quart_imp/_cli/init.py
quart_imp/_cli/filelib/__init__.py
quart_imp/_cli/filelib/api_blueprint.py
quart_imp/_cli/filelib/blueprint.py
quart_imp/_cli/filelib/extensions.py
quart_imp/_cli/filelib/favicon.py
quart_imp/_cli/filelib/head_tag_generator.py
quart_imp/_cli/filelib/init.py
quart_imp/_cli/filelib/main_js.py
quart_imp/_cli/filelib/quart_imp_logo.py
quart_imp/_cli/filelib/resources.py
quart_imp/_cli/filelib/templates.py
quart_imp/_cli/filelib/water_css.py
quart_imp/auth/__init__.py
quart_imp/auth/__legacy__.py
quart_imp/auth/__private_funcs__.py
quart_imp/auth/authenticate_password.py
quart_imp/auth/dataclasses.py
quart_imp/auth/encrypt_password.py
quart_imp/auth/generate_alphanumeric_validator.py
quart_imp/auth/generate_csrf_token.py
quart_imp/auth/generate_email_validator.py
quart_imp/auth/generate_numeric_validator.py
quart_imp/auth/generate_password.py
quart_imp/auth/generate_private_key.py
quart_imp/auth/generate_salt.py
quart_imp/auth/is_email_address_valid.py
quart_imp/auth/is_username_valid.py
quart_imp/config/__init__.py
quart_imp/config/imp_blueprint_config.py
quart_imp/config/imp_config.py
quart_imp/config/quart_config.py
quart_imp/security/__init__.py
quart_imp/security/__private_funcs__.py
quart_imp/security/api_login_check.py
quart_imp/security/include_csrf.py
quart_imp/security/login_check.py
quart_imp/security/pass_function_check.py
quart_imp/security/permission_check.py
quart_imp-1.0.0.dist-info/entry_points.txt
quart_imp-1.0.0.dist-info/LICENSE
quart_imp-1.0.0.dist-info/WHEEL
quart_imp-1.0.0.dist-info/METADATA
quart_imp-1.0.0.dist-info/RECORD
