Metadata-Version: 2.1
Name: quart-imp
Version: 1.0.0
Summary: A Quart auto importer that allows your Quart apps to grow big.
Author-email: David Carmichael <david@uilix.com>
Requires-Python: >=3.9
Classifier: Development Status :: 5 - Production/Stable
Classifier: Environment :: Web Environment
Classifier: Intended Audience :: Developers
Classifier: License :: OSI Approved :: MIT License
Classifier: Operating System :: OS Independent
Classifier: Programming Language :: Python
Classifier: Programming Language :: Python :: 3.9
Classifier: Programming Language :: Python :: 3.10
Classifier: Programming Language :: Python :: 3.11
Classifier: Programming Language :: Python :: 3.12
Classifier: Topic :: Internet :: WWW/HTTP :: Dynamic Content
Classifier: Topic :: Software Development :: Libraries :: Python Modules
Classifier: Natural Language :: English
Requires-Dist: Quart
Project-URL: Documentation, https://cheesecake87.github.io/flask-imp/
Project-URL: Source, https://github.com/CheeseCake87/flask-imp
